moat/lib/diffiehellman/__init__.py
moat/lib/diffiehellman/_impl.py
moat/lib/diffiehellman/decorators.py
moat/lib/diffiehellman/exceptions.py
moat/lib/diffiehellman/primes.py
moat_lib_diffiehellman-0.13.6.dist-info/licenses/LICENSE.txt
moat_lib_diffiehellman-0.13.6.dist-info/METADATA
moat_lib_diffiehellman-0.13.6.dist-info/WHEEL
moat_lib_diffiehellman-0.13.6.dist-info/top_level.txt
moat_lib_diffiehellman-0.13.6.dist-info/RECORD
