Metadata-Version: 2.4
Name: moat-lib-diffiehellman
Version: 0.13.6
Summary: A Pythonic implementation of the Diffie-Hellman key exchange protocol
Author-email: Matthias Urlichs <matthias@urlichs.de>, Chris von Csefalvay <chris@chrisvoncsefalvay.com>
Maintainer-email: Matthias Urlichs <matthias@urlichs.de>
Project-URL: homepage, https://m-o-a-t.org
Project-URL: repository, https://github.com/M-o-a-T/moat
Keywords: MoaT
Classifier: Development Status :: 4 - Beta
Classifier: Framework :: AnyIO
Classifier: Framework :: Trio
Classifier: Framework :: AsyncIO
Classifier: Programming Language :: Python :: 3
Classifier: Intended Audience :: Developers
Requires-Python: >=3.8
License-File: LICENSE.txt
Requires-Dist: anyio~=4.2
Dynamic: license-file
